src/test_text_with_marked_sections.py
src/text_with_marked_sections.py
text_with_marked_sections-0.1.0.dist-info/METADATA
text_with_marked_sections-0.1.0.dist-info/WHEEL
text_with_marked_sections-0.1.0.dist-info/RECORD
